commands/__init__.py
commands/create_repo.py
commands/delete_repos.py
commands/init_all.py
commands/init_git.py
commands/list_repos.py
commands/main.py
commands/pull_gitee.py
commands/set_git.py
init_gitee-0.1.8.dist-info/licenses/LICENSE
init_gitee-0.1.8.dist-info/METADATA
init_gitee-0.1.8.dist-info/WHEEL
init_gitee-0.1.8.dist-info/entry_points.txt
init_gitee-0.1.8.dist-info/top_level.txt
init_gitee-0.1.8.dist-info/RECORD
