Metadata-Version: 2.4
Name: init-gitee
Version: 0.1.8
Summary: Gitee repository initialization tool
Requires-Python: >=3.8
License-File: LICENSE
Requires-Dist: click>=8.0.0
Requires-Dist: urllib3>=1.26.0
Dynamic: license-file
